{"_type":"export","__export_format":4,"__export_date":"2020-09-14T13:33:01.123Z","__export_source":"insomnia.desktop.app:v2020.3.3","resources":[{"_id":"req_78c08eb53ab04b2fb7015efb20f6388f","authentication":{"audience":"https://api.hypertherm.com/cutchart","authorizationUrl":"https://auth0.hypertherm.com/authorize","clientId":"NlOWlPYgnE9fKkBN00pKZ87offP8n2pE","grantType":"implicit","redirectUrl":"http://localhost:5000","scope":"read","type":"oauth2"},"body":{"mimeType":"application/graphql","text":"{\"query\":\"query {\\n  products(where: {productName: \\\"XPR\\\"})\\n {\\n  productName\\n  cutCharts\\n  {\\n    id,\\n    records(where: {materialType: \\\"Mild Steel\\\" units:METRIC})\\n    {\\n      materialType,\\n      units\\n      thicknessDisplay\\n      xPRProcessFeatures\\n      nozzle\\n      tHLeadinRad\\n    }\\n  }\\n }\\n}\"}"},"created":1599830940450,"description":"","headers":[{"id":"pair_c476e40c70b14de9bac5d4731013edac","name":"Content-Type","value":"application/json"}],"isPrivate":false,"metaSortKey":-1599830940450,"method":"POST","modified":1600090256558,"name":"graphql","parameters":[],"parentId":"wrk_e4cca58abc814897a91a0241718494f5","settingDisableRenderRequestBody":false,"settingEncodeUrl":true,"settingFollowRedirects":"global","settingRebuildPath":true,"settingSendCookies":true,"settingStoreCookies":true,"url":"https://api.hypertherm.com/v2/cutchart/graphql","_type":"request"},{"_id":"wrk_e4cca58abc814897a91a0241718494f5","created":1599830929894,"description":"","modified":1599830929894,"name":"GraphQL","parentId":null,"scope":null,"_type":"workspace"},{"_id":"env_b265a407b249aebc6b0db62c1ef1d79d391d61c6","color":null,"created":1599830930176,"data":{},"dataPropertyOrder":null,"isPrivate":false,"metaSortKey":1599830930176,"modified":1599830930176,"name":"Base Environment","parentId":"wrk_e4cca58abc814897a91a0241718494f5","_type":"environment"},{"_id":"jar_b265a407b249aebc6b0db62c1ef1d79d391d61c6","cookies":[{"creation":"2020-09-14T13:16:22.191Z","domain":"ccapigraphql.azurewebsites.net","hostOnly":false,"httpOnly":true,"id":"8339984999288166","key":"ARRAffinity","lastAccessed":"2020-09-14T13:16:22.191Z","path":"/","value":"f328c1a88b05cb6439a2d82a7bb6fb824adf2f0f403726fa6a7fc75d1046ae9c"}],"created":1599830930185,"modified":1600089801230,"name":"Default Jar","parentId":"wrk_e4cca58abc814897a91a0241718494f5","_type":"cookie_jar"},{"_id":"spc_2725106f599d48e8a1143d5f37c91613","contentType":"yaml","contents":"","created":1599830929917,"fileName":"GraphQL","modified":1599830929917,"parentId":"wrk_e4cca58abc814897a91a0241718494f5","_type":"api_spec"}]}